{
    "analyses": [
        {
            "age": -8.317812151595541,
            "age_err": 4.356813733161244,
            "age_err_wo_j": 4.356813733161244,
            "baseline_corrected_intercepts": {
                "Ar36": {
                    "error": 0.001336811787924614,
                    "value": 1.7356446507193435
                },
                "Ar37": {
                    "error": 0.003940290562778334,
                    "value": 0.06393624734637943
                },
                "Ar38": {
                    "error": 0.009223462718010497,
                    "value": 0.3620060245806548
                },
                "Ar39": {
                    "error": 0.006859305361740664,
                    "value": 0.9480322303455042
                },
                "Ar40": {
                    "error": 0.03240742156212133,
                    "value": 524.9373906404315
                },
                "Ar41": {
                    "error": 0.009274251919031936,
                    "value": 0.03314177159737433
                }
            },
            "blanks": {
                "Ar36": {
                    "error": 0.00012334092498665346,
                    "value": 0.020350691875453897
                },
                "Ar37": {
                    "error": 0.0034678893778366453,
                    "value": 0.03285180186614728
                },
                "Ar38": {
                    "error": 0.007330640269036928,
                    "value": 0.019902492280685913
                },
                "Ar39": {
                    "error": 0.005438214353978233,
                    "value": 0.00198753781779043
                },
                "Ar40": {
                    "error": 0.011787425350739036,
                    "value": 5.623497314968764
                },
                "Ar41": {
                    "error": 0.00874044364735173,
                    "value": 0.0008057917532062059
                }
            },
            "extract_value": 0.25,
            "ic_corrected_values": {
                "Ar36": {
                    "error": 0.0021222367862937163,
                    "value": 1.7448221096520513
                },
                "Ar37": {
                    "error": 0.005251092373774836,
                    "value": 0.031093957447456532
                },
                "Ar38": {
                    "error": 0.011795220742650726,
                    "value": 0.3421724979274122
                },
                "Ar39": {
                    "error": 0.008782008147433398,
                    "value": 0.9461386837279573
                },
                "Ar40": {
                    "error": 0.0344845526098903,
                    "value": 519.3138933254628
                },
                "Ar41": {
                    "error": 0.012743904574744695,
                    "value": 0.032335979844168125
                }
            },
            "icfactors": {
                "Ar36": {
                    "error": 0.0009470724335850049,
                    "value": 1.0172146299798455
                },
                "Ar37": {
                    "error": 0.0022656625875133955,
                    "value": 1.0003060040826668
                },
                "Ar38": {
                    "error": 0.001492521101276402,
                    "value": 1.0002015928540102
                },
                "Ar39": {
                    "error": 0.0007355271208718935,
                    "value": 1.0000993517547172
                },
                "Ar40": {
                    "error": 0.0,
                    "value": 1.0
                },
                "Ar41": {
                    "error": 0.0,
                    "value": 1.0
                }
            },
            "interference_corrected_values": {
                "Ar36": {
                    "error": 0.0021223631625170154,
                    "value": 1.7447379067925457
                },
                "Ar37": {
                    "error": 0.052447158434030666,
                    "value": 0.3105619929164262
                },
                "Ar38": {
                    "error": 0.011795220742650726,
                    "value": 0.3421724979274122
                },
                "Ar39": {
                    "error": 0.008789323737955978,
                    "value": 0.9467004288559722
                },
                "Ar40": {
                    "error": 0.034484658464740255,
                    "value": 519.3132022341497
                },
                "Ar41": {
                    "error": 0.0,
                    "value": 0.0
                }
            },
            "kca": 1.314840080752861,
            "kca_err": 0.22258620536976742,
            "kcl": 2342.5051944300017,
            "kcl_err": 15529.984116023967,
            "plateau_step": false,
            "radiogenic_yield": -0.30727990110456704,
            "radiogenic_yield_err": 0.1605613346037282,
            "record_id": "1506-01A",
            "rundate": "2021-07-03T15:15:25.110060",
            "tag": "skip",
            "uuid": "ba97de5e-2b73-4271-bcf8-5ceffe612fa6"
        },
        {
            "age": 16.7529455043311,
            "age_err": 1.2288339279925076,
            "age_err_wo_j": 1.2288339279925076,
            "baseline_corrected_intercepts": {
                "Ar36": {
                    "error": 0.0016867532213859795,
                    "value": 2.8942201390703146
                },
                "Ar37": {
                    "error": 0.004146304306728675,
                    "value": 0.10249125739756874
                },
                "Ar38": {
                    "error": 0.010019402202199656,
                    "value": 0.6158099443528465
                },
                "Ar39": {
                    "error": 0.006854100826986989,
                    "value": 5.044432827837445
                },
                "Ar40": {
                    "error": 0.04105148562271671,
                    "value": 896.6071444535025
                },
                "Ar41": {
                    "error": 0.008575944348387784,
                    "value": 0.0468492237782252
                }
            },
            "blanks": {
                "Ar36": {
                    "error": 0.00011112092551462636,
                    "value": 0.020880036317073455
                },
                "Ar37": {
                    "error": 0.0029763804643436987,
                    "value": 0.039048783039090595
                },
                "Ar38": {
                    "error": 0.006514956169591051,
                    "value": 0.01272444627683711
                },
                "Ar39": {
                    "error": 0.004947188658396501,
                    "value": 0.005713030834579386
                },
                "Ar40": {
                    "error": 0.01101983774234523,
                    "value": 5.845557477040559
                },
                "Ar41": {
                    "error": 0.00874044364735173,
                    "value": 0.0008057917532062059
                }
            },
            "extract_value": 0.5,
            "ic_corrected_values": {
                "Ar36": {
                    "error": 0.0029745602639510227,
                    "value": 2.925932823747272
                },
                "Ar37": {
                    "error": 0.005110616018458603,
                    "value": 0.0635046616743206
                },
                "Ar38": {
                    "error": 0.011986202373234504,
                    "value": 0.6034749004289345
                },
                "Ar39": {
                    "error": 0.009085039866301488,
                    "value": 5.0403230106932
                },
                "Ar40": {
                    "error": 0.042504838497513825,
                    "value": 890.761586976462
                },
                "Ar41": {
                    "error": 0.012245087856735679,
                    "value": 0.046043432025018996
                }
            },
            "icfactors": {
                "Ar36": {
                    "error": 0.0008442766970522735,
                    "value": 1.0183036880819074
                },
                "Ar37": {
                    "error": 0.0020320797165175267,
                    "value": 1.0009802158013426
                },
                "Ar38": {
                    "error": 0.0013383390615058378,
                    "value": 1.000645683496233
                },
                "Ar39": {
                    "error": 0.0006593964365748512,
                    "value": 1.0003181787745545
                },
                "Ar40": {
                    "error": 0.0,
                    "value": 1.0
                },
                "Ar41": {
                    "error": 0.0,
                    "value": 1.0
                }
            },
            "interference_corrected_values": {
                "Ar36": {
                    "error": 0.002974702292736608,
                    "value": 2.925763473976569
                },
                "Ar37": {
                    "error": 0.051070622324359605,
                    "value": 0.6346050222696324
                },
                "Ar38": {
                    "error": 0.011986202373234504,
                    "value": 0.6034749004289345
                },
                "Ar39": {
                    "error": 0.009092602845649257,
                    "value": 5.044032435113917
                },
                "Ar40": {
                    "error": 0.042507263168656724,
                    "value": 890.7579048327843
                },
                "Ar41": {
                    "error": 0.0,
                    "value": 0.0
                }
            },
            "kca": 3.432102870623743,
            "kca_err": 0.2767895309528968,
            "kcl": -2381.6448739355014,
            "kcl_err": 3063.5287222638817,
            "plateau_step": false,
            "radiogenic_yield": 1.9356427459860295,
            "radiogenic_yield_err": 0.14258488880427034,
            "record_id": "1506-01B",
            "rundate": "2021-07-03T15:53:17.527327",
            "tag": "skip",
            "uuid": "8d18da8b-7fb2-42fe-ae76-d7ef750fbf16"
        },
        {
            "age": 51.35890540928659,
            "age_err": 0.05028395532592037,
            "age_err_wo_j": 0.05028395532592037,
            "baseline_corrected_intercepts": {
                "Ar36": {
                    "error": 0.0012545550170314258,
                    "value": 1.6332267597371066
                },
                "Ar37": {
                    "error": 0.004188293205989867,
                    "value": 0.18189980641100512
                },
                "Ar38": {
                    "error": 0.009130685521250691,
                    "value": 1.5135303295849427
                },
                "Ar39": {
                    "error": 0.012160341725472493,
                    "value": 91.86826835082051
                },
                "Ar40": {
                    "error": 0.05137968366162123,
                    "value": 1470.1141358740547
                },
                "Ar41": {
                    "error": 0.009455041495279348,
                    "value": 0.09026115708342872
                }
            },
            "blanks": {
                "Ar36": {
                    "error": 0.00012241832007158063,
                    "value": 0.021285691641846252
                },
                "Ar37": {
                    "error": 0.0031910979150885327,
                    "value": 0.04462448761769726
                },
                "Ar38": {
                    "error": 0.00710578156308125,
                    "value": 0.006856266564599367
                },
                "Ar39": {
                    "error": 0.005428746396221014,
                    "value": 0.010924508017623388
                },
                "Ar40": {
                    "error": 0.01233242051053349,
                    "value": 6.03390987122239
                },
                "Ar41": {
                    "error": 0.009137229329814037,
                    "value": 0.003704721157950619
                }
            },
            "extract_value": 1.0,
            "ic_corrected_values": {
                "Ar36": {
                    "error": 0.0017971261889422568,
                    "value": 1.644263448041006
                },
                "Ar37": {
                    "error": 0.005282819799897933,
                    "value": 0.13755839730091163
                },
                "Ar38": {
                    "error": 0.011739615814511453,
                    "value": 1.508720279934317
                },
                "Ar39": {
                    "error": 0.058458269660570925,
                    "value": 91.91880763680741
                },
                "Ar40": {
                    "error": 0.0528390053730849,
                    "value": 1464.0802260028322
                },
                "Ar41": {
                    "error": 0.013148641355785327,
                    "value": 0.0865564359254781
                }
            },
            "icfactors": {
                "Ar36": {
                    "error": 0.0007789063469688419,
                    "value": 1.0200518372448562
                },
                "Ar37": {
                    "error": 0.0019109762283079689,
                    "value": 1.0020621223836312
                },
                "Ar38": {
                    "error": 0.0012581158529802977,
                    "value": 1.0013581019041846
                },
                "Ar39": {
                    "error": 0.0006196469620170257,
                    "value": 1.000669122265387
                },
                "Ar40": {
                    "error": 0.0,
                    "value": 1.0
                },
                "Ar41": {
                    "error": 0.0,
                    "value": 1.0
                }
            },
            "interference_corrected_values": {
                "Ar36": {
                    "error": 0.001797250492450019,
                    "value": 1.6438814975850113
                },
                "Ar37": {
                    "error": 0.05283548961715018,
                    "value": 1.3757738381469224
                },
                "Ar38": {
                    "error": 0.011739615814511453,
                    "value": 1.508720279934317
                },
                "Ar39": {
                    "error": 0.05850649036835147,
                    "value": 91.99364122531301
                },
                "Ar40": {
                    "error": 0.053483747401882144,
                    "value": 1464.0130706447378
                },
                "Ar41": {
                    "error": 0.0,
                    "value": 0.0
                }
            },
            "kca": 29.260175226724506,
            "kca_err": 1.1414115673281975,
            "kcl": 4997.0945891404235,
            "kcl_err": 744.887319228858,
            "plateau_step": false,
            "radiogenic_yield": 66.47284714600565,
            "radiogenic_yield_err": 0.050562301156988995,
            "record_id": "1506-01C",
            "rundate": "2021-07-03T16:54:04.398247",
            "tag": "skip",
            "uuid": "4dcbdf2c-1bfe-4c6d-aaeb-78e6471b01de"
        },
        {
            "age": 53.89878955271513,
            "age_err": 0.039589050009647186,
            "age_err_wo_j": 0.039589050009647186,
            "baseline_corrected_intercepts": {
                "Ar36": {
                    "error": 0.001359632402678887,
                    "value": 1.8523859643921
                },
                "Ar37": {
                    "error": 0.004038292871258774,
                    "value": 0.22009823424698233
                },
                "Ar38": {
                    "error": 0.008603317086276534,
                    "value": 3.1684671111074487
                },
                "Ar39": {
                    "error": 0.018843382899117838,
                    "value": 217.27977642931745
                },
                "Ar40": {
                    "error": 0.07623902137486482,
                    "value": 2982.2708563579426
                },
                "Ar41": {
                    "error": 0.009206079429181478,
                    "value": 0.14325471598085587
                }
            },
            "blanks": {
                "Ar36": {
                    "error": 0.00011395724736487601,
                    "value": 0.021089316596863264
                },
                "Ar37": {
                    "error": 0.0028816017662797993,
                    "value": 0.04367628233617744
                },
                "Ar38": {
                    "error": 0.006431246912429351,
                    "value": 0.008918916239750288
                },
                "Ar39": {
                    "error": 0.004753585785108827,
                    "value": 0.01339251365840921
                },
                "Ar40": {
                    "error": 0.011498517489436427,
                    "value": 5.981232961500624
                },
                "Ar41": {
                    "error": 0.009137229329814037,
                    "value": 0.003704721157950619
                }
            },
            "extract_value": 1.5,
            "ic_corrected_values": {
                "Ar36": {
                    "error": 0.002037106949661093,
                    "value": 1.8700110207636191
                },
                "Ar37": {
                    "error": 0.004987245739158238,
                    "value": 0.17690457567742587
                },
                "Ar38": {
                    "error": 0.011547731472622284,
                    "value": 3.165239988930555
                },
                "Ar39": {
                    "error": 0.14320247864936467,
                    "value": 217.45919903569416
                },
                "Ar40": {
                    "error": 0.07710125994205264,
                    "value": 2976.289623396442
                },
                "Ar41": {
                    "error": 0.01297076937895406,
                    "value": 0.13954999482290525
                }
            },
            "icfactors": {
                "Ar36": {
                    "error": 0.0008115352412987551,
                    "value": 1.0211404160079647
                },
                "Ar37": {
                    "error": 0.0020147555476814423,
                    "value": 1.0027356219642383
                },
                "Ar38": {
                    "error": 0.0013261362805823361,
                    "value": 1.0018014582186472
                },
                "Ar39": {
                    "error": 0.0006530017605388412,
                    "value": 1.0008874595165627
                },
                "Ar40": {
                    "error": 0.0,
                    "value": 1.0
                },
                "Ar41": {
                    "error": 0.0,
                    "value": 1.0
                }
            },
            "interference_corrected_values": {
                "Ar36": {
                    "error": 0.0020372283361282328,
                    "value": 1.8695130785965406
                },
                "Ar37": {
                    "error": 0.0499052397954115,
                    "value": 1.7702085944490782
                },
                "Ar38": {
                    "error": 0.011547731472622284,
                    "value": 3.165239988930555
                },
                "Ar39": {
                    "error": 0.14332060071042776,
                    "value": 217.63732104747766
                },
                "Ar40": {
                    "error": 0.07955048622915174,
                    "value": 2976.1307481520776
                },
                "Ar41": {
                    "error": 0.0,
                    "value": 0.0
                }
            },
            "kca": 54.49403884588407,
            "kca_err": 1.58406782857862,
            "kcl": 5689.635547998069,
            "kcl_err": 452.45950935923355,
            "plateau_step": false,
            "radiogenic_yield": 81.2410494059039,
            "radiogenic_yield_err": 0.028239448035551267,
            "record_id": "1506-01D",
            "rundate": "2021-07-03T17:31:55.267077",
            "tag": "skip",
            "uuid": "dd7a8bb6-c53b-412e-8f87-8d08cd3c542b"
        },
        {
            "age": 54.31309986365913,
            "age_err": 0.03993317982889558,
            "age_err_wo_j": 0.03993317982889558,
            "baseline_corrected_intercepts": {
                "Ar36": {
                    "error": 0.00127287626792004,
                    "value": 1.557792960051959
                },
                "Ar37": {
                    "error": 0.004100035544772135,
                    "value": 0.5571567873222579
                },
                "Ar38": {
                    "error": 0.008728158587550355,
                    "value": 5.5412852498195
                },
                "Ar39": {
                    "error": 0.023718409445491626,
                    "value": 405.0452535145123
                },
                "Ar40": {
                    "error": 0.10828476418216447,
                    "value": 5021.55076304722
                },
                "Ar41": {
                    "error": 0.00945191383319442,
                    "value": 0.16337101459682038
                }
            },
            "blanks": {
                "Ar36": {
                    "error": 0.0001278752464573853,
                    "value": 0.02131008345119701
                },
                "Ar37": {
                    "error": 0.003284596366400054,
                    "value": 0.047818580624657214
                },
                "Ar38": {
                    "error": 0.00739001439237954,
                    "value": 0.01946670774308079
                },
                "Ar39": {
                    "error": 0.0056392624147298415,
                    "value": 0.013252074318191642
                },
                "Ar40": {
                    "error": 0.011780288344674785,
                    "value": 6.096899518277409
                },
                "Ar41": {
                    "error": 0.009044898251128213,
                    "value": 0.006143554853373631
                }
            },
            "extract_value": 2.0,
            "ic_corrected_values": {
                "Ar36": {
                    "error": 0.0019075367224490056,
                    "value": 1.5728689481704408
                },
                "Ar37": {
                    "error": 0.00540149305595636,
                    "value": 0.5118436321238465
                },
                "Ar38": {
                    "error": 0.014071130401087916,
                    "value": 5.539698403995318
                },
                "Ar39": {
                    "error": 0.2950177731089684,
                    "value": 405.6778605968087
                },
                "Ar40": {
                    "error": 0.1089236675267164,
                    "value": 5015.453863528943
                },
                "Ar41": {
                    "error": 0.013082387377057532,
                    "value": 0.15722745974344676
                }
            },
            "icfactors": {
                "Ar36": {
                    "error": 0.0009026948408192546,
                    "value": 1.0236814038892366
                },
                "Ar37": {
                    "error": 0.002242910725199585,
                    "value": 1.0049189819128046
                },
                "Ar38": {
                    "error": 0.00147521564239436,
                    "value": 1.0032380386611137
                },
                "Ar39": {
                    "error": 0.0007258821127780291,
                    "value": 1.0015945879691435
                },
                "Ar40": {
                    "error": 0.0,
                    "value": 1.0
                },
                "Ar41": {
                    "error": 0.0,
                    "value": 1.0
                }
            },
            "interference_corrected_values": {
                "Ar36": {
                    "error": 0.0019076683609182204,
                    "value": 1.5714464594633262
                },
                "Ar37": {
                    "error": 0.054155122150521984,
                    "value": 5.131720828386028
                },
                "Ar38": {
                    "error": 0.014071130401087916,
                    "value": 5.539698403995318
                },
                "Ar39": {
                    "error": 0.2952613228088138,
                    "value": 406.0091504953401
                },
                "Ar40": {
                    "error": 0.11488970184750452,
                    "value": 5015.157476849081
                },
                "Ar41": {
                    "error": 0.0,
                    "value": 0.0
                }
            },
            "kca": 34.71766779174061,
            "kca_err": 0.37654172152790505,
            "kcl": 5762.750986550363,
            "kcl_err": 352.80470591602705,
            "plateau_step": false,
            "radiogenic_yield": 90.63958209184065,
            "radiogenic_yield_err": 0.01496233954875133,
            "record_id": "1506-01E",
            "rundate": "2021-07-03T19:53:00.068852",
            "tag": "skip",
            "uuid": "adab5356-0807-4f1d-a730-c485441d2980"
        },
        {
            "age": 54.56880310218088,
            "age_err": 0.03497753605293077,
            "age_err_wo_j": 0.03497753605293077,
            "baseline_corrected_intercepts": {
                "Ar36": {
                    "error": 0.0008581699288703682,
                    "value": 0.8433703222098695
                },
                "Ar37": {
                    "error": 0.004219137120555743,
                    "value": 0.48816794163188354
                },
                "Ar38": {
                    "error": 0.009187171319579497,
                    "value": 7.409663595357448
                },
                "Ar39": {
                    "error": 0.027599129760096267,
                    "value": 559.1382615044824
                },
                "Ar40": {
                    "error": 0.13997910431750907,
                    "value": 6563.627002850578
                },
                "Ar41": {
                    "error": 0.008525237529173816,
                    "value": 0.20775206725248913
                }
            },
            "blanks": {
                "Ar36": {
                    "error": 0.00011987704916469277,
                    "value": 0.022477669680760294
                },
                "Ar37": {
                    "error": 0.0029253137573537163,
                    "value": 0.04220442705237726
                },
                "Ar38": {
                    "error": 0.006823580468611795,
                    "value": 0.010237776354756645
                },
                "Ar39": {
                    "error": 0.005079437007743172,
                    "value": 0.028072234083026837
                },
                "Ar40": {
                    "error": 0.010985910649261053,
                    "value": 6.510402986643978
                },
                "Ar41": {
                    "error": 0.009044898251128213,
                    "value": 0.006143554853373631
                }
            },
            "extract_value": 2.5,
            "ic_corrected_values": {
                "Ar36": {
                    "error": 0.0011146158024048002,
                    "value": 0.8402961006660815
                },
                "Ar37": {
                    "error": 0.005237710365305069,
                    "value": 0.4483487756616779
                },
                "Ar38": {
                    "error": 0.015040630867107496,
                    "value": 7.425475937928692
                },
                "Ar39": {
                    "error": 0.36215005137920453,
                    "value": 560.0794587018598
                },
                "Ar40": {
                    "error": 0.1404095434018843,
                    "value": 6557.1165998639335
                },
                "Ar41": {
                    "error": 0.012429394969269255,
                    "value": 0.20160851239911548
                }
            },
            "icfactors": {
                "Ar36": {
                    "error": 0.0008222784807171704,
                    "value": 1.023637010365718
                },
                "Ar37": {
                    "error": 0.0019959516823084356,
                    "value": 1.0053485565616744
                },
                "Ar38": {
                    "error": 0.0013125934109590128,
                    "value": 1.0035205595086987
                },
                "Ar39": {
                    "error": 0.0006457713753579521,
                    "value": 1.0017335928589055
                },
                "Ar40": {
                    "error": 0.0,
                    "value": 1.0
                },
                "Ar41": {
                    "error": 0.0,
                    "value": 1.0
                }
            },
            "interference_corrected_values": {
                "Ar36": {
                    "error": 0.0011147601787497123,
                    "value": 0.8390258146960822
                },
                "Ar37": {
                    "error": 0.05254031176130644,
                    "value": 4.497458394626708
                },
                "Ar38": {
                    "error": 0.015040630867107496,
                    "value": 7.425475937928692
                },
                "Ar39": {
                    "error": 0.36244908403489773,
                    "value": 560.5387585225099
                },
                "Ar40": {
                    "error": 0.1491977206711764,
                    "value": 6556.707406570212
                },
                "Ar41": {
                    "error": 0.0,
                    "value": 0.0
                }
            },
            "kca": 55.264681317468074,
            "kca_err": 0.6747689863036372,
            "kcl": 5407.05112673,
            "kcl_err": 272.8708637155816,
            "plateau_step": true,
            "radiogenic_yield": 96.17348972359908,
            "radiogenic_yield_err": 0.006488162479315611,
            "record_id": "1506-01F",
            "rundate": "2021-07-03T20:30:51.031449",
            "tag": "ok",
            "uuid": "d9f4c259-6de3-4512-857f-7a2361ad9fc5"
        },
        {
            "age": 54.6690492407626,
            "age_err": 0.03211574686647884,
            "age_err_wo_j": 0.03211574686647884,
            "baseline_corrected_intercepts": {
                "Ar36": {
                    "error": 0.0012846300706510132,
                    "value": 0.5951276390783679
                },
                "Ar37": {
                    "error": 0.004369142285921972,
                    "value": 0.8557240991521281
                },
                "Ar38": {
                    "error": 0.010724197161052799,
                    "value": 8.908530184076277
                },
                "Ar39": {
                    "error": 0.032368178442883325,
                    "value": 679.2507143244543
                },
                "Ar40": {
                    "error": 0.170042226233419,
                    "value": 7858.191229284514
                },
                "Ar41": {
                    "error": 0.008701359715149595,
                    "value": 0.2466087832547058
                }
            },
            "blanks": {
                "Ar36": {
                    "error": 0.00013409269295434187,
                    "value": 0.02412533471841978
                },
                "Ar37": {
                    "error": 0.003202598011249841,
                    "value": 0.03666572194463254
                },
                "Ar38": {
                    "error": 0.0075617241820311095,
                    "value": 0.004232222578579747
                },
                "Ar39": {
                    "error": 0.005596323779143795,
                    "value": 0.04240955714420163
                },
                "Ar40": {
                    "error": 0.012237209090023703,
                    "value": 7.114264877257801
                },
                "Ar41": {
                    "error": 0.008642711075762437,
                    "value": 0.01252726164349599
                }
            },
            "extract_value": 3.0,
            "ic_corrected_values": {
                "Ar36": {
                    "error": 0.001400135457194098,
                    "value": 0.5844583394421378
                },
                "Ar37": {
                    "error": 0.0056523663795288205,
                    "value": 0.8240046969958477
                },
                "Ar38": {
                    "error": 0.016982101204844828,
                    "value": 8.939688825979097
                },
                "Ar39": {
                    "error": 0.4033986388732977,
                    "value": 680.5374732521518
                },
                "Ar40": {
                    "error": 0.17048198728525604,
                    "value": 7851.076964407256
                },
                "Ar41": {
                    "error": 0.012264180185871982,
                    "value": 0.23408152161120982
                }
            },
            "icfactors": {
                "Ar36": {
                    "error": 0.0008074464164424663,
                    "value": 1.0235656405927696
                },
                "Ar37": {
                    "error": 0.0018304324847386233,
                    "value": 1.0060390320470394
                },
                "Ar38": {
                    "error": 0.0012034614468280243,
                    "value": 1.0039745822337067
                },
                "Ar39": {
                    "error": 0.000591944688791448,
                    "value": 1.0019569379165603
                },
                "Ar40": {
                    "error": 0.0,
                    "value": 1.0
                },
                "Ar41": {
                    "error": 0.0,
                    "value": 1.0
                }
            },
            "interference_corrected_values": {
                "Ar36": {
                    "error": 0.0014002876548899017,
                    "value": 0.5821561988060292
                },
                "Ar37": {
                    "error": 0.05674713746140635,
                    "value": 8.272625068788576
                },
                "Ar38": {
                    "error": 0.016982101204844828,
                    "value": 8.939688825979097
                },
                "Ar39": {
                    "error": 0.4037318591095589,
                    "value": 681.093788411107
                },
                "Ar40": {
                    "error": 0.18116758461401622,
                    "value": 7850.579765941716
                },
                "Ar41": {
                    "error": 0.0,
                    "value": 0.0
                }
            },
            "kca": 36.15427800065076,
            "kca_err": 0.25820826869010527,
            "kcl": 5410.990347673545,
            "kcl_err": 264.2688343010088,
            "plateau_step": true,
            "radiogenic_yield": 97.77984913444001,
            "radiogenic_yield_err": 0.0058524661697098605,
            "record_id": "1506-01G",
            "rundate": "2021-07-03T21:31:42.403927",
            "tag": "ok",
            "uuid": "296f2e06-ec13-434e-8be7-493878e5fe02"
        },
        {
            "age": 54.646454668542994,
            "age_err": 0.03331101347089853,
            "age_err_wo_j": 0.03331101347089853,
            "baseline_corrected_intercepts": {
                "Ar36": {
                    "error": 0.0005139414263311136,
                    "value": 0.2496770962332867
                },
                "Ar37": {
                    "error": 0.0040247928549672655,
                    "value": 0.846233593283565
                },
                "Ar38": {
                    "error": 0.009640437489957753,
                    "value": 4.832127342259018
                },
                "Ar39": {
                    "error": 0.02361527636751924,
                    "value": 370.95362677755463
                },
                "Ar40": {
                    "error": 0.11164981152947585,
                    "value": 4266.7494680072505
                },
                "Ar41": {
                    "error": 0.008911280805470358,
                    "value": 0.15280339019628442
                }
            },
            "blanks": {
                "Ar36": {
                    "error": 0.00012384423037406535,
                    "value": 0.02492002940329778
                },
                "Ar37": {
                    "error": 0.002963363239472417,
                    "value": 0.03674054719811275
                },
                "Ar38": {
                    "error": 0.0068199042924323265,
                    "value": 0.009420614696177776
                },
                "Ar39": {
                    "error": 0.005224984526125941,
                    "value": 0.04174842327651976
                },
                "Ar40": {
                    "error": 0.011129306634600308,
                    "value": 7.4289460497207624
                },
                "Ar41": {
                    "error": 0.008642711075762437,
                    "value": 0.01252726164349599
                }
            },
            "extract_value": 3.5,
            "ic_corrected_values": {
                "Ar36": {
                    "error": 0.000575510011327198,
                    "value": 0.23004361575524654
                },
                "Ar37": {
                    "error": 0.005260230365624,
                    "value": 0.8147298142505415
                },
                "Ar38": {
                    "error": 0.013301101299145131,
                    "value": 4.843238833954825
                },
                "Ar39": {
                    "error": 0.22911093064246235,
                    "value": 371.6893201925548
                },
                "Ar40": {
                    "error": 0.1122031277671636,
                    "value": 4259.320521957529
                },
                "Ar41": {
                    "error": 0.012413999368980617,
                    "value": 0.14027612855278843
                }
            },
            "icfactors": {
                "Ar36": {
                    "error": 0.000872289864736823,
                    "value": 1.0235211688772237
                },
                "Ar37": {
                    "error": 0.0018998933770845924,
                    "value": 1.0064691947514721
                },
                "Ar38": {
                    "error": 0.0012489479951950549,
                    "value": 1.0042573823273637
                },
                "Ar39": {
                    "error": 0.0006142303479812649,
                    "value": 1.0020960284198128
                },
                "Ar40": {
                    "error": 0.0,
                    "value": 1.0
                },
                "Ar41": {
                    "error": 0.0,
                    "value": 1.0
                }
            },
            "interference_corrected_values": {
                "Ar36": {
                    "error": 0.0005757298149597311,
                    "value": 0.22780019047643066
                },
                "Ar37": {
                    "error": 0.05283775033932616,
                    "value": 8.18376525878045
                },
                "Ar38": {
                    "error": 0.013301101299145131,
                    "value": 4.843238833954825
                },
                "Ar39": {
                    "error": 0.2293002421222952,
                    "value": 371.990659043559
                },
                "Ar40": {
                    "error": 0.11709151979643012,
                    "value": 4259.0489687764275
                },
                "Ar41": {
                    "error": 0.0,
                    "value": 0.0
                }
            },
            "kca": 19.794087007024228,
            "kca_err": 0.13051535749880086,
            "kcl": 5843.134133380749,
            "kcl_err": 366.97809837634844,
            "plateau_step": true,
            "radiogenic_yield": 98.39684340030924,
            "radiogenic_yield_err": 0.004433364243969802,
            "record_id": "1506-01H",
            "rundate": "2021-07-03T22:09:37.913439",
            "tag": "ok",
            "uuid": "97009b73-804f-4580-adc1-7d413900c4f1"
        },
        {
            "age": 54.651125053508615,
            "age_err": 0.03682768731065943,
            "age_err_wo_j": 0.03682768731065943,
            "baseline_corrected_intercepts": {
                "Ar36": {
                    "error": 0.0005396830067632335,
                    "value": 0.29740543936609626
                },
                "Ar37": {
                    "error": 0.004020119781494092,
                    "value": 2.314538356640013
                },
                "Ar38": {
                    "error": 0.009034190488938412,
                    "value": 5.872301677606529
                },
                "Ar39": {
                    "error": 0.02584211936574331,
                    "value": 450.59296135824445
                },
                "Ar40": {
                    "error": 0.11711288333687213,
                    "value": 5181.22380685304
                },
                "Ar41": {
                    "error": 0.008547456873666403,
                    "value": 0.15653541770223237
                }
            },
            "blanks": {
                "Ar36": {
                    "error": 0.00014263417875521868,
                    "value": 0.025979101505416734
                },
                "Ar37": {
                    "error": 0.0033236325099338677,
                    "value": 0.03961213924092975
                },
                "Ar38": {
                    "error": 0.00749279813636318,
                    "value": 0.006194437505875505
                },
                "Ar39": {
                    "error": 0.005209219932556269,
                    "value": 0.01239187249957674
                },
                "Ar40": {
                    "error": 0.01240940470866889,
                    "value": 7.499536861805076
                },
                "Ar41": {
                    "error": 0.008879101871284765,
                    "value": -0.0024185704182066725
                }
            },
            "extract_value": 4.0,
            "ic_corrected_values": {
                "Ar36": {
                    "error": 0.0006314267093092774,
                    "value": 0.277885241102158
                },
                "Ar37": {
                    "error": 0.007111761393592921,
                    "value": 2.290645529133961
                },
                "Ar38": {
                    "error": 0.014319899653553778,
                    "value": 5.892780503314159
                },
                "Ar39": {
                    "error": 0.30808437285116197,
                    "value": 451.589174994072
                },
                "Ar40": {
                    "error": 0.11776850499475382,
                    "value": 5173.724269991235
                },
                "Ar41": {
                    "error": 0.012324669125288502,
                    "value": 0.15895398812043904
                }
            },
            "icfactors": {
                "Ar36": {
                    "error": 0.000989210874387784,
                    "value": 1.0237961551277082
                },
                "Ar37": {
                    "error": 0.002107757323511765,
                    "value": 1.0069098116741781
                },
                "Ar38": {
                    "error": 0.0013853862754812853,
                    "value": 1.0045470125454181
                },
                "Ar39": {
                    "error": 0.000681230815369313,
                    "value": 1.0022384576180865
                },
                "Ar40": {
                    "error": 0.0,
                    "value": 1.0
                },
                "Ar41": {
                    "error": 0.0,
                    "value": 1.0
                }
            },
            "interference_corrected_values": {
                "Ar36": {
                    "error": 0.0006318279414849478,
                    "value": 0.2716152122148092
                },
                "Ar37": {
                    "error": 0.0715744408518947,
                    "value": 23.053595848331184
                },
                "Ar38": {
                    "error": 0.014319899653553778,
                    "value": 5.892780503314159
                },
                "Ar39": {
                    "error": 0.30833924819439446,
                    "value": 451.9464005245932
                },
                "Ar40": {
                    "error": 0.12459510977410738,
                    "value": 5173.394349118852
                },
                "Ar41": {
                    "error": 0.0,
                    "value": 0.0
                }
            },
            "kca": 8.48734004776335,
            "kca_err": 0.027230875477671782,
            "kcl": 5688.725435369163,
            "kcl_err": 327.0371131945156,
            "plateau_step": true,
            "radiogenic_yield": 98.42621379914831,
            "radiogenic_yield_err": 0.00406964897384582,
            "record_id": "1506-01I",
            "rundate": "2021-07-04T00:30:51.714063",
            "tag": "ok",
            "uuid": "64a3d9cf-5048-4646-a8f2-9ba15ca573e2"
        },
        {
            "age": 54.619454935776986,
            "age_err": 0.03392642531454367,
            "age_err_wo_j": 0.03392642531454367,
            "baseline_corrected_intercepts": {
                "Ar36": {
                    "error": 0.00043681058006609486,
                    "value": 0.1619996617030782
                },
                "Ar37": {
                    "error": 0.004185766437420541,
                    "value": 3.3764259340759355
                },
                "Ar38": {
                    "error": 0.00962670842400869,
                    "value": 2.756944411576551
                },
                "Ar39": {
                    "error": 0.017012806365489127,
                    "value": 208.66830199321436
                },
                "Ar40": {
                    "error": 0.06976647632617075,
                    "value": 2402.731428241382
                },
                "Ar41": {
                    "error": 0.008683762643127436,
                    "value": 0.10128305525668851
                }
            },
            "blanks": {
                "Ar36": {
                    "error": 0.0001331075753571712,
                    "value": 0.025888977913375664
                },
                "Ar37": {
                    "error": 0.0029232863322383455,
                    "value": 0.03856267842967635
                },
                "Ar38": {
                    "error": 0.0067595120892250645,
                    "value": -0.0036011638270032065
                },
                "Ar39": {
                    "error": 0.004786165970711537,
                    "value": 0.03789611504688639
                },
                "Ar40": {
                    "error": 0.011386990104028166,
                    "value": 7.736296258535894
                },
                "Ar41": {
                    "error": 0.008879101871284765,
                    "value": -0.0024185704182066725
                }
            },
            "extract_value": 5.0,
            "ic_corrected_values": {
                "Ar36": {
                    "error": 0.0004826702997391622,
                    "value": 0.13938841662070062
                },
                "Ar37": {
                    "error": 0.008223475422441421,
                    "value": 3.3594636222828167
                },
                "Ar38": {
                    "error": 0.01231786586491919,
                    "value": 2.77230212214205
                },
                "Ar39": {
                    "error": 0.13094173458016242,
                    "value": 209.06784419010495
                },
                "Ar40": {
                    "error": 0.07068963688263917,
                    "value": 2394.9951319828465
                },
                "Ar41": {
                    "error": 0.012419588708279682,
                    "value": 0.10370162567489519
                }
            },
            "icfactors": {
                "Ar36": {
                    "error": 0.0008781274121502159,
                    "value": 1.0240813780354108
                },
                "Ar37": {
                    "error": 0.0019234899209724086,
                    "value": 1.0064713156238556
                },
                "Ar38": {
                    "error": 0.001264458933551941,
                    "value": 1.0042587765415818
                },
                "Ar39": {
                    "error": 0.0006218581613694406,
                    "value": 1.0020967140915833
                },
                "Ar40": {
                    "error": 0.0,
                    "value": 1.0
                },
                "Ar41": {
                    "error": 0.0,
                    "value": 1.0
                }
            },
            "interference_corrected_values": {
                "Ar36": {
                    "error": 0.000483403765867574,
                    "value": 0.13022070547452644
                },
                "Ar37": {
                    "error": 0.08280609903509609,
                    "value": 33.828042660941655
                },
                "Ar38": {
                    "error": 0.01231786586491919,
                    "value": 2.77230212214205
                },
                "Ar39": {
                    "error": 0.13105067172101698,
                    "value": 209.21700949433665
                },
                "Ar40": {
                    "error": 0.07315452923074979,
                    "value": 2394.8424035659154
                },
                "Ar41": {
                    "error": 0.0,
                    "value": 0.0
                }
            },
            "kca": 2.669526365718953,
            "kca_err": 0.006760419080657657,
            "kcl": 4493.5676377643,
            "kcl_err": 305.2346813217518,
            "plateau_step": true,
            "radiogenic_yield": 98.37029220969266,
            "radiogenic_yield_err": 0.006306781495174128,
            "record_id": "1506-01J",
            "rundate": "2021-07-04T01:08:49.642178",
            "tag": "ok",
            "uuid": "375c49aa-e9f4-4a5f-b6d6-98b23f10deb2"
        },
        {
            "age": 54.52207173570357,
            "age_err": 0.034636548277747814,
            "age_err_wo_j": 0.034636548277747814,
            "baseline_corrected_intercepts": {
                "Ar36": {
                    "error": 0.0005564966724096822,
                    "value": 0.09433178765320017
                },
                "Ar37": {
                    "error": 0.004597512312326347,
                    "value": 1.3664342924157702
                },
                "Ar38": {
                    "error": 0.009652498538371478,
                    "value": 1.5673869090752504
                },
                "Ar39": {
                    "error": 0.015609894203393149,
                    "value": 118.2959296162918
                },
                "Ar40": {
                    "error": 0.05480888627570742,
                    "value": 1360.427037382283
                },
                "Ar41": {
                    "error": 0.00881045294159138,
                    "value": 0.041475022563662464
                }
            },
            "blanks": {
                "Ar36": {
                    "error": 0.00016283947984627306,
                    "value": 0.025716895194508732
                },
                "Ar37": {
                    "error": 0.0034965531717704806,
                    "value": 0.03754918806016022
                },
                "Ar38": {
                    "error": 0.008159274920856089,
                    "value": -0.01026771858894357
                },
                "Ar39": {
                    "error": 0.005823057764700894,
                    "value": 0.0549646394710544
                },
                "Ar40": {
                    "error": 0.013844232530775295,
                    "value": 7.878853946590962
                },
                "Ar41": {
                    "error": 0.009315249002908609,
                    "value": -0.0031546901723304432
                }
            },
            "extract_value": 6.0,
            "ic_corrected_values": {
                "Ar36": {
                    "error": 0.0005965870027867531,
                    "value": 0.07029862552364416
                },
                "Ar37": {
                    "error": 0.00633363466047588,
                    "value": 1.3365498620136478
                },
                "Ar38": {
                    "error": 0.012838961057371607,
                    "value": 1.5836438038765914
                },
                "Ar39": {
                    "error": 0.07450750180109206,
                    "value": 118.46198329151025
                },
                "Ar40": {
                    "error": 0.056530317433653304,
                    "value": 1352.5481834356922
                },
                "Ar41": {
                    "error": 0.012821776203872301,
                    "value": 0.04462971273599291
                }
            },
            "icfactors": {
                "Ar36": {
                    "error": 0.0007993404926093554,
                    "value": 1.0245388865976346
                },
                "Ar37": {
                    "error": 0.0018986470213268232,
                    "value": 1.0057678106503831
                },
                "Ar38": {
                    "error": 0.0012484255573551103,
                    "value": 1.003796253062855
                },
                "Ar39": {
                    "error": 0.0006141164371502905,
                    "value": 1.0018692194767933
                },
                "Ar40": {
                    "error": 0.0,
                    "value": 1.0
                },
                "Ar41": {
                    "error": 0.0,
                    "value": 1.0
                }
            },
            "interference_corrected_values": {
                "Ar36": {
                    "error": 0.0005968883513109044,
                    "value": 0.06664084444224136
                },
                "Ar37": {
                    "error": 0.06382968656970307,
                    "value": 13.469605266228145
                },
                "Ar38": {
                    "error": 0.012838961057371607,
                    "value": 1.5836438038765914
                },
                "Ar39": {
                    "error": 0.07456933456691078,
                    "value": 118.55053877150743
                },
                "Ar40": {
                    "error": 0.05752841921480306,
                    "value": 1352.461641542389
                },
                "Ar41": {
                    "error": 0.0,
                    "value": 0.0
                }
            },
            "kca": 3.80117386806802,
            "kca_err": 0.01821619233560416,
            "kcl": 4004.0731220464754,
            "kcl_err": 410.1409556972309,
            "plateau_step": false,
            "radiogenic_yield": 98.52257888815325,
            "radiogenic_yield_err": 0.013287466140210386,
            "record_id": "1506-01K",
            "rundate": "2021-07-04T02:09:43.918156",
            "tag": "skip",
            "uuid": "613a083d-3ce8-4e6d-ab72-46cfdf4b0158"
        },
        {
            "age": 54.56457564289498,
            "age_err": 0.036322058255414326,
            "age_err_wo_j": 0.036322058255414326,
            "baseline_corrected_intercepts": {
                "Ar36": {
                    "error": 0.000367043061594526,
                    "value": 0.12529760557484737
                },
                "Ar37": {
                    "error": 0.003915598316601589,
                    "value": 1.6520357024370396
                },
                "Ar38": {
                    "error": 0.0090789042854699,
                    "value": 2.1157378635973125
                },
                "Ar39": {
                    "error": 0.014491886728002638,
                    "value": 161.01147673917453
                },
                "Ar40": {
                    "error": 0.060554023451104604,
                    "value": 1852.3417948948345
                },
                "Ar41": {
                    "error": 0.008744207656004189,
                    "value": 0.07386911896155043
                }
            },
            "blanks": {
                "Ar36": {
                    "error": 0.00013575647486875354,
                    "value": 0.02558179298455642
                },
                "Ar37": {
                    "error": 0.002996980276363856,
                    "value": 0.037595970167889244
                },
                "Ar38": {
                    "error": 0.0068489275408753925,
                    "value": -0.005261843429378715
                },
                "Ar39": {
                    "error": 0.00489092502720873,
                    "value": 0.04145871891077263
                },
                "Ar40": {
                    "error": 0.011611283629314125,
                    "value": 7.727481243117438
                },
                "Ar41": {
                    "error": 0.009315249002908609,
                    "value": -0.0031546901723304432
                }
            },
            "extract_value": 8.0,
            "ic_corrected_values": {
                "Ar36": {
                    "error": 0.00040942058683651305,
                    "value": 0.10219115635626867
                },
                "Ar37": {
                    "error": 0.005966397604827973,
                    "value": 1.6230436177339442
                },
                "Ar38": {
                    "error": 0.011767429696431334,
                    "value": 2.128439997778539
                },
                "Ar39": {
                    "error": 0.10820079044158808,
                    "value": 161.24807327038428
                },
                "Ar40": {
                    "error": 0.06165721096220055,
                    "value": 1844.614313651717
                },
                "Ar41": {
                    "error": 0.012776346563768224,
                    "value": 0.07702380913388088
                }
            },
            "icfactors": {
                "Ar36": {
                    "error": 0.0008255595811864659,
                    "value": 1.0248239842977396
                },
                "Ar37": {
                    "error": 0.0020566141149046583,
                    "value": 1.005329332085194
                },
                "Ar38": {
                    "error": 0.001352495539743645,
                    "value": 1.0035079169163479
                },
                "Ar39": {
                    "error": 0.0006654067267684807,
                    "value": 1.0017273729203753
                },
                "Ar40": {
                    "error": 0.0,
                    "value": 1.0
                },
                "Ar41": {
                    "error": 0.0,
                    "value": 1.0
                }
            },
            "interference_corrected_values": {
                "Ar36": {
                    "error": 0.0004098185056001933,
                    "value": 0.09774988866394038
                },
                "Ar37": {
                    "error": 0.060160005755566716,
                    "value": 16.36537151084238
                },
                "Ar38": {
                    "error": 0.011767429696431334,
                    "value": 2.128439997778539
                },
                "Ar39": {
                    "error": 0.10829051754829709,
                    "value": 161.37002563063328
                },
                "Ar40": {
                    "error": 0.06334464636227567,
                    "value": 1844.4965135330067
                },
                "Ar41": {
                    "error": 0.0,
                    "value": 0.0
                }
            },
            "kca": 4.259604918626971,
            "kca_err": 0.01596786141114403,
            "kcl": 4769.470140617563,
            "kcl_err": 409.70765263587197,
            "plateau_step": false,
            "radiogenic_yield": 98.41148327531904,
            "radiogenic_yield_err": 0.006878927475855406,
            "record_id": "1506-01L",
            "rundate": "2021-07-04T02:47:40.174434",
            "tag": "skip",
            "uuid": "b10e9447-c325-47b4-992a-0b1ae295f768"
        },
        {
            "age": 54.20640087562752,
            "age_err": 0.09036168278271067,
            "age_err_wo_j": 0.09036168278271067,
            "baseline_corrected_intercepts": {
                "Ar36": {
                    "error": 0.00020330432344164049,
                    "value": 0.03822151437189166
                },
                "Ar37": {
                    "error": 0.0042009537906944625,
                    "value": 0.16291175542681244
                },
                "Ar38": {
                    "error": 0.009242725418961569,
                    "value": 0.09748144298533931
                },
                "Ar39": {
                    "error": 0.00707624882587746,
                    "value": 7.4524492127788475
                },
                "Ar40": {
                    "error": 0.01858851854587263,
                    "value": 94.60820316050868
                },
                "Ar41": {
                    "error": 0.008984404775785692,
                    "value": 0.010271446722126265
                }
            },
            "blanks": {
                "Ar36": {
                    "error": 0.00013927124806425108,
                    "value": 0.025062278032002595
                },
                "Ar37": {
                    "error": 0.00343218474880519,
                    "value": 0.03893266809580392
                },
                "Ar38": {
                    "error": 0.007237321844966337,
                    "value": 0.006893281519951666
                },
                "Ar39": {
                    "error": 0.005229993372191197,
                    "value": 0.0036712951635769764
                },
                "Ar40": {
                    "error": 0.012191112251757815,
                    "value": 7.257447578540592
                },
                "Ar41": {
                    "error": 0.00872383068584884,
                    "value": 0.009324582981957333
                }
            },
            "extract_value": 10.0,
            "ic_corrected_values": {
                "Ar36": {
                    "error": 0.00025306290526572357,
                    "value": 0.013498119646840192
                },
                "Ar37": {
                    "error": 0.0054568339704012215,
                    "value": 0.12453717007211909
                },
                "Ar38": {
                    "error": 0.011774721789712941,
                    "value": 0.09085660888655327
                },
                "Ar39": {
                    "error": 0.010453593454662928,
                    "value": 7.4596489163757305
                },
                "Ar40": {
                    "error": 0.022229625270463065,
                    "value": 87.35075558196809
                },
                "Ar41": {
                    "error": 0.01252296893753708,
                    "value": 0.0009468637401689323
                }
            },
            "icfactors": {
                "Ar36": {
                    "error": 0.000910563732981857,
                    "value": 1.0257525055556516
                },
                "Ar37": {
                    "error": 0.0023321500576052603,
                    "value": 1.0045014264350935
                },
                "Ar38": {
                    "error": 0.001534127980911032,
                    "value": 1.0029633830383917
                },
                "Ar39": {
                    "error": 0.0007549748465028456,
                    "value": 1.0014594338669638
                },
                "Ar40": {
                    "error": 0.0,
                    "value": 1.0
                },
                "Ar41": {
                    "error": 0.0,
                    "value": 1.0
                }
            },
            "interference_corrected_values": {
                "Ar36": {
                    "error": 0.0002535212142812193,
                    "value": 0.013159074675254128
                },
                "Ar37": {
                    "error": 0.055128821484868876,
                    "value": 1.2581631499834338
                },
                "Ar38": {
                    "error": 0.011774721789712941,
                    "value": 0.09085660888655327
                },
                "Ar39": {
                    "error": 0.0104623340306012,
                    "value": 7.46494410047266
                },
                "Ar40": {
                    "error": 0.02223977683474146,
                    "value": 87.34530617277474
                },
                "Ar41": {
                    "error": 0.0,
                    "value": 0.0
                }
            },
            "kca": 2.5608208198503446,
            "kca_err": 0.11242759294466725,
            "kcl": -14008.140848787136,
            "kcl_err": 70280.21263302777,
            "plateau_step": false,
            "radiogenic_yield": 95.49606329329868,
            "radiogenic_yield_err": 0.08678886711257705,
            "record_id": "1506-01M",
            "rundate": "2021-07-04T05:09:04.638538",
            "tag": "skip",
            "uuid": "ff45d110-736d-432e-915a-e56d7372859d"
        },
        {
            "age": 54.3516791421364,
            "age_err": 0.07035686649595368,
            "age_err_wo_j": 0.07035686649595368,
            "baseline_corrected_intercepts": {
                "Ar36": {
                    "error": 0.00020827042331783623,
                    "value": 0.034970846118178994
                },
                "Ar37": {
                    "error": 0.004002689356090116,
                    "value": 0.23722726548157114
                },
                "Ar38": {
                    "error": 0.009112702172841101,
                    "value": 0.14818696680300908
                },
                "Ar39": {
                    "error": 0.0075180046723499734,
                    "value": 10.067028665824607
                },
                "Ar40": {
                    "error": 0.020131146231777416,
                    "value": 123.11777967272506
                },
                "Ar41": {
                    "error": 0.0083539675558003,
                    "value": 0.02218445563313881
                }
            },
            "blanks": {
                "Ar36": {
                    "error": 0.00012541024777902758,
                    "value": 0.024900776325255596
                },
                "Ar37": {
                    "error": 0.0030256109089979717,
                    "value": 0.04087762427575798
                },
                "Ar38": {
                    "error": 0.0064534374433511624,
                    "value": 0.001292665607643434
                },
                "Ar39": {
                    "error": 0.004980396592248083,
                    "value": 0.01062883468509393
                },
                "Ar40": {
                    "error": 0.010631457693399496,
                    "value": 7.259465984786109
                },
                "Ar41": {
                    "error": 0.00872383068584884,
                    "value": 0.009324582981957333
                }
            },
            "extract_value": 12.0,
            "ic_corrected_values": {
                "Ar36": {
                    "error": 0.00024955893812720476,
                    "value": 0.01033126565229758
                },
                "Ar37": {
                    "error": 0.005057143179243368,
                    "value": 0.19726557730020572
                },
                "Ar38": {
                    "error": 0.01120244385275571,
                    "value": 0.1473453936655434
                },
                "Ar39": {
                    "error": 0.011246624723864266,
                    "value": 10.071608387167263
                },
                "Ar40": {
                    "error": 0.022766004069483724,
                    "value": 115.85831368793896
                },
                "Ar41": {
                    "error": 0.012078658690381223,
                    "value": 0.012859872651181478
                }
            },
            "icfactors": {
                "Ar36": {
                    "error": 0.0008280128677121829,
                    "value": 1.0259378400294439
                },
                "Ar37": {
                    "error": 0.0020588659032702013,
                    "value": 1.0046648218390808
                },
                "Ar38": {
                    "error": 0.001354281861398093,
                    "value": 1.0030708643324278
                },
                "Ar39": {
                    "error": 0.0006664327816744058,
                    "value": 1.001512326109057
                },
                "Ar40": {
                    "error": 0.0,
                    "value": 1.0
                },
                "Ar41": {
                    "error": 0.0,
                    "value": 1.0
                }
            },
            "interference_corrected_values": {
                "Ar36": {
                    "error": 0.00024996094502781113,
                    "value": 0.009788610630697737
                },
                "Ar37": {
                    "error": 0.05111747119872044,
                    "value": 1.9939553041586846
                },
                "Ar38": {
                    "error": 0.01120244385275571,
                    "value": 0.1473453936655434
                },
                "Ar39": {
                    "error": 0.011256024354319298,
                    "value": 10.078552265103788
                },
                "Ar40": {
                    "error": 0.022784068650195426,
                    "value": 115.85095634478543
                },
                "Ar41": {
                    "error": 0.0,
                    "value": 0.0
                }
            },
            "kca": 2.1811560781092076,
            "kca_err": 0.05604111380815975,
            "kcl": 1929.8176050573752,
            "kcl_err": 940.1488272630935,
            "plateau_step": false,
            "radiogenic_yield": 97.47118282685688,
            "radiogenic_yield_err": 0.06447334975136323,
            "record_id": "1506-01N",
            "rundate": "2021-07-04T05:47:02.595079",
            "tag": "skip",
            "uuid": "be0e2980-c1bc-4012-9f03-da4e8930fa6b"
        },
        {
            "age": 54.371882129174196,
            "age_err": 0.04572936989585265,
            "age_err_wo_j": 0.04572936989585265,
            "baseline_corrected_intercepts": {
                "Ar36": {
                    "error": 0.0002283663433252811,
                    "value": 0.0500402517019875
                },
                "Ar37": {
                    "error": 0.004091226301265304,
                    "value": 0.5648960813781664
                },
                "Ar38": {
                    "error": 0.009285461913315647,
                    "value": 0.27780660657871403
                },
                "Ar39": {
                    "error": 0.0078039887739791225,
                    "value": 20.05389256263866
                },
                "Ar40": {
                    "error": 0.022007716403769802,
                    "value": 239.6592871570116
                },
                "Ar41": {
                    "error": 0.008859763798537123,
                    "value": 0.0027038426382768044
                }
            },
            "blanks": {
                "Ar36": {
                    "error": 0.00013807533842262348,
                    "value": 0.02446863401638473
                },
                "Ar37": {
                    "error": 0.003291891843915552,
                    "value": 0.041983420685687826
                },
                "Ar38": {
                    "error": 0.007075627295253117,
                    "value": -0.003424246786688921
                },
                "Ar39": {
                    "error": 0.0055607763702131855,
                    "value": 0.016573391261970032
                },
                "Ar40": {
                    "error": 0.011496285084144804,
                    "value": 7.13726886879882
                },
                "Ar41": {
                    "error": 0.008953627771559346,
                    "value": 0.02141280991017408
                }
            },
            "extract_value": 15.0,
            "ic_corrected_values": {
                "Ar36": {
                    "error": 0.00027464580636576426,
                    "value": 0.026242513043072083
                },
                "Ar37": {
                    "error": 0.005363913524573059,
                    "value": 0.5254893714209594
                },
                "Ar38": {
                    "error": 0.011716891588425456,
                    "value": 0.2821430860747068
                },
                "Ar39": {
                    "error": 0.015306514344907115,
                    "value": 20.06932640365056
                },
                "Ar40": {
                    "error": 0.024829501647127127,
                    "value": 232.52201828821276
                },
                "Ar41": {
                    "error": 0.012596144840287751,
                    "value": -0.018708967271897275
                }
            },
            "icfactors": {
                "Ar36": {
                    "error": 0.0008094790675629877,
                    "value": 1.026235937269117
                },
                "Ar37": {
                    "error": 0.0018387165537346287,
                    "value": 1.0049276120510615
                },
                "Ar38": {
                    "error": 0.001209363994750245,
                    "value": 1.0032437148996542
                },
                "Ar39": {
                    "error": 0.0005950676955448481,
                    "value": 1.0015973809669907
                },
                "Ar40": {
                    "error": 0.0,
                    "value": 1.0
                },
                "Ar41": {
                    "error": 0.0,
                    "value": 1.0
                }
            },
            "interference_corrected_values": {
                "Ar36": {
                    "error": 0.0002750648275839112,
                    "value": 0.024800796857463128
                },
                "Ar37": {
                    "error": 0.05426372818613108,
                    "value": 5.316083543266569
                },
                "Ar38": {
                    "error": 0.011716891588425456,
                    "value": 0.2821430860747068
                },
                "Ar39": {
                    "error": 0.015319379293742537,
                    "value": 20.08222658949335
                },
                "Ar40": {
                    "error": 0.024895199804144494,
                    "value": 232.50735826280243
                },
                "Ar41": {
                    "error": 0.0,
                    "value": 0.0
                }
            },
            "kca": 1.6296702298339558,
            "kca_err": 0.016698690709472323,
            "kcl": 2651.5223691479823,
            "kcl_err": 932.5695589847429,
            "plateau_step": false,
            "radiogenic_yield": 96.8092544569356,
            "radiogenic_yield_err": 0.03548311603720953,
            "record_id": "1506-01O",
            "rundate": "2021-07-04T06:48:06.674974",
            "tag": "skip",
            "uuid": "b37df431-6ef5-4f4e-af70-157d48d78006"
        },
        {
            "age": 54.37483275893801,
            "age_err": 0.036792231948594,
            "age_err_wo_j": 0.036792231948594,
            "baseline_corrected_intercepts": {
                "Ar36": {
                    "error": 0.00031441209654845453,
                    "value": 0.09045603997641889
                },
                "Ar37": {
                    "error": 0.004124041140590628,
                    "value": 2.798772957220943
                },
                "Ar38": {
                    "error": 0.00927321079143323,
                    "value": 0.6142929882428179
                },
                "Ar39": {
                    "error": 0.0094731257563164,
                    "value": 45.3628591922992
                },
                "Ar40": {
                    "error": 0.03312912301303715,
                    "value": 534.4345566648135
                },
                "Ar41": {
                    "error": 0.008992944292378362,
                    "value": 0.03732756922197003
                }
            },
            "blanks": {
                "Ar36": {
                    "error": 0.00012895059345096203,
                    "value": 0.024026641699320974
                },
                "Ar37": {
                    "error": 0.0030277665922723174,
                    "value": 0.04063567696488406
                },
                "Ar38": {
                    "error": 0.006618566593905207,
                    "value": -0.002037958820324672
                },
                "Ar39": {
                    "error": 0.004862283495307239,
                    "value": 0.014989292722886478
                },
                "Ar40": {
                    "error": 0.010499417251449518,
                    "value": 6.935115533300985
                },
                "Ar41": {
                    "error": 0.008953627771559346,
                    "value": 0.02141280991017408
                }
            },
            "extract_value": 20.0,
            "ic_corrected_values": {
                "Ar36": {
                    "error": 0.00035358777694603056,
                    "value": 0.06818454205610439
                },
                "Ar37": {
                    "error": 0.007291809794903271,
                    "value": 2.7721787126906796
                },
                "Ar38": {
                    "error": 0.011456288962499022,
                    "value": 0.6183963444524927
                },
                "Ar39": {
                    "error": 0.02950161283423842,
                    "value": 45.42270417743099
                },
                "Ar40": {
                    "error": 0.034753079780545836,
                    "value": 527.4994411315125
                },
                "Ar41": {
                    "error": 0.0126901732579764,
                    "value": 0.01591475931179595
                }
            },
            "icfactors": {
                "Ar36": {
                    "error": 0.0008723374143206618,
                    "value": 1.0264211903844924
                },
                "Ar37": {
                    "error": 0.0018744294785480258,
                    "value": 1.005090911368022
                },
                "Ar38": {
                    "error": 0.0012327848222503772,
                    "value": 1.0033511174462226
                },
                "Ar39": {
                    "error": 0.0006065589859501054,
                    "value": 1.0016502269681111
                },
                "Ar40": {
                    "error": 0.0,
                    "value": 1.0
                },
                "Ar41": {
                    "error": 0.0,
                    "value": 1.0
                }
            },
            "interference_corrected_values": {
                "Ar36": {
                    "error": 0.00035434768544471024,
                    "value": 0.06059507166183602
                },
                "Ar37": {
                    "error": 0.07380559251433669,
                    "value": 28.05919218967791
                },
                "Ar38": {
                    "error": 0.011456288962499022,
                    "value": 0.6183963444524927
                },
                "Ar39": {
                    "error": 0.029528031141652308,
                    "value": 45.44065830293413
                },
                "Ar40": {
                    "error": 0.03499288972962493,
                    "value": 527.4662694509514
                },
                "Ar41": {
                    "error": 0.0,
                    "value": 0.0
                }
            },
            "kca": 0.69829517035362,
            "kca_err": 0.0018935291754739268,
            "kcl": 3685.155661600749,
            "kcl_err": 783.1902292017583,
            "plateau_step": false,
            "radiogenic_yield": 96.56408426954138,
            "radiogenic_yield_err": 0.020385462568814544,
            "record_id": "1506-01P",
            "rundate": "2021-07-04T07:26:03.982023",
            "tag": "skip",
            "uuid": "865ead82-cb7d-4d50-8a64-3f408b7db0d3"
        },
        {
            "age": 55.126795142190424,
            "age_err": 0.6608794800522554,
            "age_err_wo_j": 0.6608794800522554,
            "baseline_corrected_intercepts": {
                "Ar36": {
                    "error": 0.00016867783776539663,
                    "value": 0.024859126370637783
                },
                "Ar37": {
                    "error": 0.004174827855618257,
                    "value": 0.16632927604157385
                },
                "Ar38": {
                    "error": 0.008136440533265767,
                    "value": 0.0195789841878311
                },
                "Ar39": {
                    "error": 0.0067140005799647415,
                    "value": 0.8844746661337477
                },
                "Ar40": {
                    "error": 0.016379073166737347,
                    "value": 16.98563592920917
                },
                "Ar41": {
                    "error": 0.008851393345629828,
                    "value": 0.022612875007616134
                }
            },
            "blanks": {
                "Ar36": {
                    "error": 0.00014244044186502154,
                    "value": 0.023765981777578073
                },
                "Ar37": {
                    "error": 0.003251088815445244,
                    "value": 0.05032146096685543
                },
                "Ar38": {
                    "error": 0.007228882760675541,
                    "value": 0.002151035463281173
                },
                "Ar39": {
                    "error": 0.005579214305291796,
                    "value": 0.0021351241883606487
                },
                "Ar40": {
                    "error": 0.012004962160115958,
                    "value": 6.701185885825808
                },
                "Ar41": {
                    "error": 0.008748578711465673,
                    "value": -0.013098780528779816
                }
            },
            "extract_value": 25.0,
            "ic_corrected_values": {
                "Ar36": {
                    "error": 0.00022646862798774155,
                    "value": 0.001121326523411384
                },
                "Ar37": {
                    "error": 0.005322439031805519,
                    "value": 0.1165888151243325
                },
                "Ar38": {
                    "error": 0.010919763369141739,
                    "value": 0.017485404727173665
                },
                "Ar39": {
                    "error": 0.008760509318991454,
                    "value": 0.8837720097758874
                },
                "Ar40": {
                    "error": 0.020307465481126673,
                    "value": 10.284450043383362
                },
                "Ar41": {
                    "error": 0.012445271938763346,
                    "value": 0.03571165553639595
                }
            },
            "icfactors": {
                "Ar36": {
                    "error": 0.0009060833379630207,
                    "value": 1.0257806062716672
                },
                "Ar37": {
                    "error": 0.001897154939368714,
                    "value": 1.0050082837026098
                },
                "Ar38": {
                    "error": 0.0012477660229234227,
                    "value": 1.003296773678408
                },
                "Ar39": {
                    "error": 0.0006139469513816994,
                    "value": 1.001623488195193
                },
                "Ar40": {
                    "error": 0.0,
                    "value": 1.0
                },
                "Ar41": {
                    "error": 0.0,
                    "value": 1.0
                }
            },
            "interference_corrected_values": {
                "Ar36": {
                    "error": 0.00022695669794772823,
                    "value": 0.0008006160009720037
                },
                "Ar37": {
                    "error": 0.05397686477897021,
                    "value": 1.182371215734088
                },
                "Ar38": {
                    "error": 0.010919763369141739,
                    "value": 0.017485404727173665
                },
                "Ar39": {
                    "error": 0.008767870505081517,
                    "value": 0.8836751737211227
                },
                "Ar40": {
                    "error": 0.02030762222360895,
                    "value": 10.283804960506545
                },
                "Ar41": {
                    "error": 0.0,
                    "value": 0.0
                }
            },
            "kca": 0.32219851378265124,
            "kca_err": 0.01506822256383328,
            "kcl": 592.0974727853725,
            "kcl_err": 983.5743671021502,
            "plateau_step": false,
            "radiogenic_yield": 97.66952053716068,
            "radiogenic_yield_err": 0.6588815933078337,
            "record_id": "1506-01Q",
            "rundate": "2021-07-04T09:47:35.794705",
            "tag": "skip",
            "uuid": "7a30eb59-6ac2-436a-baa5-751fa0b824a8"
        },
        {
            "age": 68.19208603228313,
            "age_err": 14.63030030818901,
            "age_err_wo_j": 14.63030030818901,
            "baseline_corrected_intercepts": {
                "Ar36": {
                    "error": 0.0001762474512286773,
                    "value": 0.02394934030244454
                },
                "Ar37": {
                    "error": 0.004087478332207364,
                    "value": 0.04880703436671087
                },
                "Ar38": {
                    "error": 0.009395277079682048,
                    "value": 0.00815372931399963
                },
                "Ar39": {
                    "error": 0.006908781754116177,
                    "value": 0.0548644312740181
                },
                "Ar40": {
                    "error": 0.015928053569827856,
                    "value": 7.441878343408803
                },
                "Ar41": {
                    "error": 0.009128167800390757,
                    "value": -0.0179514024173532
                }
            },
            "blanks": {
                "Ar36": {
                    "error": 0.00011761421226585184,
                    "value": 0.02329435589372103
                },
                "Ar37": {
                    "error": 0.002972454488609496,
                    "value": 0.04756097355123828
                },
                "Ar38": {
                    "error": 0.006690623784135459,
                    "value": -0.0011113544581850474
                },
                "Ar39": {
                    "error": 0.004845800608134905,
                    "value": 0.01044716816868932
                },
                "Ar40": {
                    "error": 0.01083031455210473,
                    "value": 6.614797609421052
                },
                "Ar41": {
                    "error": 0.008748578711465673,
                    "value": -0.013098780528779816
                }
            },
            "extract_value": 35.0,
            "ic_corrected_values": {
                "Ar36": {
                    "error": 0.00021717918073733467,
                    "value": 0.0006713402994886743
                },
                "Ar37": {
                    "error": 0.005077532118073239,
                    "value": 0.0012518613275450958
                },
                "Ar38": {
                    "error": 0.011569460306605198,
                    "value": 0.009293476213333289
                },
                "Ar39": {
                    "error": 0.008451557677679609,
                    "value": 0.04448429642115365
                },
                "Ar40": {
                    "error": 0.019261324041218907,
                    "value": 0.8270807339877511
                },
                "Ar41": {
                    "error": 0.012643618028982092,
                    "value": -0.004852621888573383
                }
            },
            "icfactors": {
                "Ar36": {
                    "error": 0.0008171033385629799,
                    "value": 1.0249714200022553
                },
                "Ar37": {
                    "error": 0.0018010948654123555,
                    "value": 1.004655079431499
                },
                "Ar38": {
                    "error": 0.001184729016562608,
                    "value": 1.003064455956011
                },
                "Ar39": {
                    "error": 0.0005829988827831349,
                    "value": 1.0015091725860261
                },
                "Ar40": {
                    "error": 0.0,
                    "value": 1.0
                },
                "Ar41": {
                    "error": 0.0,
                    "value": 1.0
                }
            },
            "interference_corrected_values": {
                "Ar36": {
                    "error": 0.00021764469013881151,
                    "value": 0.0006662213652306091
                },
                "Ar37": {
                    "error": 0.051520016009505336,
                    "value": 0.012702217167122139
                },
                "Ar38": {
                    "error": 0.011569460306605198,
                    "value": 0.009293476213333289
                },
                "Ar39": {
                    "error": 0.008458648099092397,
                    "value": 0.044512292514031535
                },
                "Ar40": {
                    "error": 0.019261325447591664,
                    "value": 0.8270482400142158
                },
                "Ar41": {
                    "error": 0.0,
                    "value": 0.0
                }
            },
            "kca": 1.5116577755399532,
            "kca_err": 6.1440381087265505,
            "kcl": 22.730205439714496,
            "kcl_err": 30.82852612828426,
            "plateau_step": false,
            "radiogenic_yield": 75.94678045302744,
            "radiogenic_yield_err": 7.876532275496432,
            "record_id": "1506-01R",
            "rundate": "2021-07-04T10:25:35.839048",
            "tag": "skip",
            "uuid": "6f555b1c-1257-4d4d-bcd8-6f399c8d4b03"
        }
    ],
    "name": "01",
    "preferred": {
        "age": 54.632114920683605,
        "age_err": 0.01738236732896176,
        "ages": {
            "integrated_age": 54.36947870871902,
            "integrated_age_err": 0.03927850386381352,
            "isochron_age": 54.69685981347626,
            "isochron_age_err": 0.055490680544959155,
            "plateau_age": 54.632114920683605,
            "plateau_age_err": 0.01738236732896176,
            "weighted_age": 54.632114920683605,
            "weighted_age_err": 0.041722850368336735
        },
        "arar_constants": {
            "abundance_sensitivity": 0.0,
            "atm4036": 298.56,
            "atm4036_err": 0.31,
            "atm4038": 1583.87,
            "atm4038_err": 3.01,
            "fixed_k3739": 4.252,
            "fixed_k3739_err": 0.001,
            "lambda_Ar37": 0.01975,
            "lambda_Ar37_err": 0.0,
            "lambda_Ar39": 7.068e-06,
            "lambda_Ar39_err": 0.0,
            "lambda_Cl36": 6.308e-09,
            "lambda_Cl36_err": 0.0,
            "lambda_k": 5.463e-10,
            "lambda_k_err": 9.998499887483122e-12
        },
        "display_age_units": "Ma",
        "include_j_error_in_mean": true,
        "include_j_error_in_plateau": true,
        "include_j_position_error": false,
        "mswd": 1.2974896813560304,
        "nanalyses": 5,
        "preferred_kinds": [
            {
                "attr": "age",
                "error": 0.01738236732896176,
                "error_kind": "SEM, but if MSWD>1 use SEM * sqrt(MSWD)",
                "kind": "Plateau",
                "value": 54.632114920683605,
                "weighting": ""
            },
            {
                "attr": "kca",
                "error": 0.02409455761533548,
                "error_kind": "SD",
                "kind": "Plateau else Valid Integrated",
                "value": 12.68024075025064,
                "weighting": ""
            },
            {
                "attr": "kcl",
                "error": 136.99943202924277,
                "error_kind": "SD",
                "kind": "Plateau else Valid Integrated",
                "value": 5426.38505273011,
                "weighting": ""
            },
            {
                "attr": "radiogenic_yield",
                "error": 0.0026814190732065,
                "error_kind": "SD",
                "kind": "Plateau else Valid Integrated",
                "value": 97.65990475381724,
                "weighting": ""
            },
            {
                "attr": "moles_k39",
                "error": 6.776390810385382e-18,
                "error_kind": "SD",
                "kind": "Plateau else Valid Integrated",
                "value": 2.2747866159961062e-14,
                "weighting": ""
            },
            {
                "attr": "signal_k39",
                "error": 0.6776390810385381,
                "error_kind": "SD",
                "kind": "Plateau else Valid Integrated",
                "value": 2274.786615996106,
                "weighting": ""
            }
        ]
    },
    "sample_metadata": {
        "grainsize": "",
        "irradiation": "UA002",
        "irradiation_level": "E",
        "irradiation_position": 4,
        "latitude": 0.0,
        "lithology": "",
        "lithology_class": "",
        "lithology_group": "",
        "lithology_type": "",
        "longitude": 0.0,
        "material": "Biotite",
        "principal_investigator": "",
        "project": "Coast Sheer Zone (SE Alaska)",
        "rlocation": "",
        "sample": "M9630H1",
        "unit": ""
    },
    "uuid": "63d801c2-7064-48d9-bb2b-629edbf516e2"
}